MANIFEST.in
README.txt
plone3buildout.cfg
setup.cfg
setup.py
collective/__init__.py
collective.groupdelegation.egg-info/PKG-INFO
collective.groupdelegation.egg-info/SOURCES.txt
collective.groupdelegation.egg-info/dependency_links.txt
collective.groupdelegation.egg-info/entry_points.txt
collective.groupdelegation.egg-info/namespace_packages.txt
collective.groupdelegation.egg-info/not-zip-safe
collective.groupdelegation.egg-info/requires.txt
collective.groupdelegation.egg-info/top_level.txt
collective/groupdelegation/__init__.py
collective/groupdelegation/configure.zcml
collective/groupdelegation/profiles.zcml
collective/groupdelegation/readme.txt
collective/groupdelegation/setuphandlers.py
collective/groupdelegation/skins.zcml
collective/groupdelegation/tests.py
collective/groupdelegation/update-l10n.sh
collective/groupdelegation/i18n/collective.groupdelegation-fr.po
collective/groupdelegation/i18n/collective.groupdelegation-plone-en.po
collective/groupdelegation/i18n/collective.groupdelegation-plone-fr.po
collective/groupdelegation/i18n/collective.groupdelegation-plone-manual.pot
collective/groupdelegation/i18n/collective.groupdelegation.pot
collective/groupdelegation/profiles/default/actions.xml
collective/groupdelegation/profiles/default/groupdelegation_marker.txt
collective/groupdelegation/profiles/default/metadata.xml
collective/groupdelegation/profiles/default/skins.xml
collective/groupdelegation/skins/groupdelegation/get_delegated_groups.py
collective/groupdelegation/skins/groupdelegation/prefs_deleg_group_members.cpt
collective/groupdelegation/skins/groupdelegation/prefs_deleg_group_members.cpt.metadata
collective/groupdelegation/skins/groupdelegation/prefs_deleg_group_members_add.cpy
collective/groupdelegation/skins/groupdelegation/prefs_deleg_group_members_add.cpy.metadata
collective/groupdelegation/skins/groupdelegation/prefs_deleg_group_members_delete.cpy
collective/groupdelegation/skins/groupdelegation/prefs_deleg_group_members_delete.cpy.metadata
collective/groupdelegation/skins/groupdelegation/prefs_deleg_groups_overview.cpt
collective/groupdelegation/skins/groupdelegation/prefs_deleg_groups_overview.cpt.metadata
collective/groupdelegation/skins/groupdelegation/prefs_group_details.pt
collective/groupdelegation/skins/groupdelegation/prefs_group_details.pt.metadata
collective/groupdelegation/skins/groupdelegation/prefs_group_managers.cpt
