Metadata-Version: 1.0
Name: collective.groupdelegation
Version: 0.4
Summary: Plone Groups Management Delegation
Home-page: http://pypi.python.org/pypi/collective.groupdelegation
Author: Ingeniweb
Author-email: support@ingeniweb.com
License: GPL
Keywords: Zope Plone Groups Delegation
Platform: UNKNOWN
Classifier: Framework :: Plone
Classifier: Programming Language :: Python
Classifier: Topic :: Software Development :: Libraries :: Python Modules
